pushchamp/__init__.py
pushchamp-0.0.1.dist-info/DESCRIPTION.rst
pushchamp-0.0.1.dist-info/METADATA
pushchamp-0.0.1.dist-info/RECORD
pushchamp-0.0.1.dist-info/WHEEL
pushchamp-0.0.1.dist-info/metadata.json
pushchamp-0.0.1.dist-info/top_level.txt
